<?xml version="1.0" encoding="UTF-8"?>
<ivdnt:modal type="help" suppress-ok-button="true" style="width: 70vw" xmlns:ivdnt="http://www.ivdnt.org/xslt/namespaces">
    <ivdnt:modaltrigger><button type="button" name="help" class="helpknop btn btn-default">Help...</button></ivdnt:modaltrigger>
    <ivdnt:modalcontent modal-body-class="gtb-modal-body">
        <ivdnt:modaltitle><h3 class="modal-title">Help</h3></ivdnt:modaltitle>
        
        <ivdnt:retrieve-help-text from-tab-with-id="resultaat"/>
        
        <div class="modal-footer">
            <p><button type="button" name="annuleer-help" class="btn btn-default" data-dismiss="modal" >Ok</button></p>
        </div>
    </ivdnt:modalcontent>
</ivdnt:modal>
